{
	"format_version": "1.8.0",
	"animations": {
		"idle": {
			"loop": true,
			"animation_length": 2.25,
			"bones": {
				"body": {
					"rotation": {
						"0.0": {
							"vector": [0, 0, 0]
						},
						"0.75": {
							"vector": [10, 0, 0]
						},
						"2.2083": {
							"vector": [0, 0, 0]
						}
					}
				},
				"left_arm_down": {
					"rotation": {
						"0.0": {
							"vector": [0, 0, 0]
						},
						"0.75": {
							"vector": [0, 17.5, 0]
						},
						"2.2083": {
							"vector": [0, 0, 0]
						}
					}
				},
				"right_arm_down": {
					"rotation": {
						"0.0": {
							"vector": [0, 0, 0]
						},
						"0.75": {
							"vector": [0, -12.5, 0]
						},
						"2.2083": {
							"vector": [0, 0, 0]
						}
					}
				},
				"right_leg": {
					"position": {
						"0.0": {
							"vector": [0, 0, 0]
						},
						"0.7083": {
							"vector": [0, -2, 0]
						},
						"2.2083": {
							"vector": [0, 0, 0]
						}
					},
					"scale": {
						"0.0": {
							"vector": [1, 1, 1]
						},
						"0.7083": {
							"vector": [1, 0.91, 1]
						},
						"2.2083": {
							"vector": [1, 1, 1]
						}
					}
				},
				"left_leg": {
					"position": {
						"0.0": {
							"vector": [0, 0, 0]
						},
						"0.75": {
							"vector": [0, -2.5, 0]
						},
						"2.2083": {
							"vector": [0, 0, 0]
						}
					},
					"scale": {
						"0.0": {
							"vector": [1, 1, 1]
						},
						"0.75": {
							"vector": [1, 0.92, 1]
						},
						"2.2083": {
							"vector": [1, 1, 1]
						}
					}
				}
			}
		},
		"Walk": {
			"loop": true,
			"animation_length": 2.0417,
			"bones": {
				"body": {
					"rotation": {
						"0.0": {
							"vector": [7.5, -7.5, 0]
						},
						"0.25": {
							"vector": [7.5, -7.5, 0]
						},
						"0.8333": {
							"vector": [7.7451, 9.7777, 0.5947]
						},
						"1.375": {
							"vector": [0, 0, 0]
						},
						"1.6667": {
							"vector": [7.5, -7.5, 0]
						},
						"1.8333": {
							"vector": [7.5, -7.5, 0]
						},
						"1.9583": {
							"vector": [7.5, -7.5, 0]
						}
					},
					"position": {
						"0.0": {
							"vector": [0, -0.9, 0]
						},
						"0.25": {
							"vector": [0, -0.9, 0]
						},
						"1.375": {
							"vector": [0, 0, 0]
						},
						"1.6667": {
							"vector": [0, -0.9, 0]
						},
						"1.8333": {
							"vector": [0, -0.9, 0]
						},
						"1.9583": {
							"vector": [0, -0.9, 0]
						}
					}
				},
				"head": {
					"rotation": {
						"0.8333": {
							"vector": [10, 7.5, 0]
						},
						"1.375": {
							"vector": [0, 0, 0]
						},
						"1.9583": {
							"vector": [10, 7.5, 0]
						}
					}
				},
				"jaw": {
					"rotation": {
						"0.4583": {
							"vector": [0, 0, 0]
						},
						"0.8333": {
							"vector": [-32.5, 0, 0]
						},
						"1.1667": {
							"vector": [0, 0, 0]
						},
						"1.375": {
							"vector": [0, 0, 0]
						}
					}
				},
				"left_arm": {
					"rotation": {
						"0.0": {
							"vector": [0, 0, 0]
						},
						"0.8333": {
							"vector": [-25.8545, 24.7556, -2.8369]
						},
						"1.375": {
							"vector": [0, 0, 0]
						},
						"2.0": {
							"vector": [0, 0, 0]
						}
					},
					"position": {
						"0.0": {
							"vector": [0, 0, 0]
						},
						"0.8333": {
							"vector": [0, 1, 0]
						},
						"1.375": {
							"vector": [0, 0, 0]
						},
						"2.0": {
							"vector": [0, 0, 0]
						}
					}
				},
				"left_arm_down": {
					"rotation": {
						"0.4167": {
							"vector": [-15, 18.93, 0]
						},
						"0.8333": {
							"vector": [0, 12.5, 0]
						},
						"1.375": {
							"vector": [0, 0, 0]
						},
						"1.9583": {
							"vector": [-15, 18.93, 0]
						}
					}
				},
				"right_arm": {
					"rotation": {
						"0.0": {
							"vector": [-10, -12.5, 0]
						},
						"0.25": {
							"vector": [-10.1067, -14.9616, 0.4492]
						},
						"1.375": {
							"vector": [0, 0, 0]
						},
						"1.6667": {
							"vector": [-10, -12.5, 0]
						},
						"1.8333": {
							"vector": [-10.1067, -14.9616, 0.4492]
						},
						"1.9583": {
							"vector": [-10, -12.5, 0]
						}
					},
					"position": {
						"0.25": {
							"vector": [0, 2, 0]
						},
						"1.8333": {
							"vector": [0, 2, 0]
						}
					}
				},
				"right_arm_down": {
					"rotation": {
						"0.0": {
							"vector": [0, -32.5, 0]
						},
						"0.25": {
							"vector": [0, -42.5, 0]
						},
						"1.375": {
							"vector": [0, 0, 0]
						},
						"1.6667": {
							"vector": [0, -32.5, 0]
						},
						"1.8333": {
							"vector": [0, -42.5, 0]
						},
						"1.9583": {
							"vector": [0, -32.5, 0]
						}
					}
				},
				"right_leg": {
					"rotation": {
						"0.25": {
							"vector": [-30, 0, 0]
						},
						"0.6667": {
							"vector": [-7.5, 0, 0]
						},
						"1.5417": {
							"vector": [0, 0, 0]
						},
						"1.9583": {
							"vector": [-30, 0, 0]
						}
					},
					"position": {
						"0.25": {
							"vector": [0, 0, -0.6]
						},
						"0.6667": {
							"vector": [0, -2, -0.6]
						},
						"1.5417": {
							"vector": [0, 0, 0]
						},
						"1.9583": {
							"vector": [0, 0, -0.6]
						}
					}
				},
				"right_leg_down": {
					"rotation": {
						"0.25": {
							"vector": [15, 0, 0]
						},
						"0.6667": {
							"vector": [5, 0, 0]
						},
						"1.0417": {
							"vector": [5, 0, 0]
						},
						"1.5417": {
							"vector": [5, 0, 0]
						},
						"1.6667": {
							"vector": [15, 0, 0]
						},
						"1.9583": {
							"vector": [15, 0, 0]
						}
					}
				},
				"right_foot": {
					"rotation": {
						"0.6667": {
							"vector": [-2.5, 0, 0]
						},
						"1.5417": {
							"vector": [0, 0, 0]
						}
					}
				},
				"left_leg": {
					"rotation": {
						"0.4167": {
							"vector": [0, 0, 0]
						},
						"0.9167": {
							"vector": [-27.5, 0, 0]
						},
						"1.4167": {
							"vector": [-20, 0, 0]
						},
						"1.5417": {
							"vector": [0, 0, 0]
						},
						"1.6667": {
							"vector": [0, 0, 0]
						},
						"1.9583": {
							"vector": [0, 0, 0]
						}
					},
					"position": {
						"0.9167": {
							"vector": [0, 0, -2]
						},
						"1.3333": {
							"vector": [0, -0.7, -0.89]
						},
						"1.5417": {
							"vector": [0, 0, 0]
						},
						"1.9583": {
							"vector": [0, 0, -2]
						}
					}
				},
				"left_leg_down": {
					"rotation": {
						"0.9167": {
							"vector": [15, 0, 0]
						},
						"1.3333": {
							"vector": [15, 0, 0]
						},
						"1.4167": {
							"vector": [12.5, 0, 0]
						},
						"1.5417": {
							"vector": [0, 0, 0]
						},
						"1.9583": {
							"vector": [15, 0, 0]
						}
					},
					"position": {
						"1.4167": {
							"vector": [0, -1, 0]
						},
						"1.5417": {
							"vector": [0, 0, 0]
						}
					}
				},
				"left_foot": {
					"rotation": {
						"0.9167": {
							"vector": [12.5, 0, 0]
						},
						"1.5417": {
							"vector": [0, 0, 0]
						},
						"1.9583": {
							"vector": [12.5, 0, 0]
						}
					}
				}
			}
		},
		"attack": {
			"animation_length": 1.125,
			"bones": {
				"body": {
					"rotation": {
						"0.0": {
							"vector": [0, -10, 0]
						},
						"0.125": {
							"vector": [17.6754, -14.9416, -1.3378]
						},
						"1.0": {
							"vector": [0, 0, 0]
						}
					}
				},
				"head": {
					"rotation": {
						"0.0": {
							"vector": [0, 0, 0]
						},
						"0.75": {
							"vector": [0, 12.5, 0]
						},
						"1.0417": {
							"vector": [0, 5, 0]
						}
					}
				},
				"jaw": {
					"rotation": {
						"0.0": {
							"vector": [0, 0, 0]
						},
						"0.5833": {
							"vector": [0, 0, 0]
						},
						"0.75": {
							"vector": [-37.5, 0, 0]
						},
						"0.875": {
							"vector": [0, 0, 0]
						}
					}
				},
				"left_arm": {
					"rotation": {
						"0.0": {
							"vector": [0, 0, 0]
						},
						"0.4167": {
							"vector": [-8.7597, 11.8903, 1.5268]
						},
						"1.0417": {
							"vector": [0, 0, 0]
						}
					}
				},
				"left_arm_down": {
					"rotation": {
						"0.0": {
							"vector": [0, 0, 0]
						},
						"0.4167": {
							"vector": [-9.9315, 14.3836, -2.5577]
						},
						"1.0417": {
							"vector": [0, 0, 0]
						}
					}
				},
				"right_arm": {
					"rotation": {
						"0.0": {
							"vector": [0, 0, 0]
						},
						"0.125": {
							"vector": [0, -35, 0]
						},
						"0.2917": {
							"vector": [-4.6575, -36.5125, -32.5845]
						},
						"0.5": {
							"vector": [-8.6441, -25.1778, -12.8159]
						},
						"0.7917": {
							"vector": [-11.6017, -10.4908, -5.34]
						},
						"1.0": {
							"vector": [0, 0, 0]
						}
					},
					"position": {
						"0.0": {
							"vector": [0, 0, 0]
						},
						"0.2917": {
							"vector": [-2.2, 0, 0]
						},
						"0.5": {
							"vector": [-1.47, -0.4, 0]
						},
						"0.7917": {
							"vector": [-0.61, 0.03, 0]
						},
						"1.0": {
							"vector": [0, 0, 0]
						}
					}
				},
				"right_arm_down": {
					"rotation": {
						"0.0": {
							"vector": [0, 0, 0]
						},
						"0.125": {
							"vector": [-56.7731, 8.5268, -62.8297]
						},
						"0.2917": {
							"vector": [-48.0597, -2.1251, -61.1603]
						},
						"1.0": {
							"vector": [0, 0, 0]
						}
					}
				}
			}
		}
	}
}